PrintWithColor/PrintWithColor.py
PrintWithColor/PrintWithColorCore.py
PrintWithColor-0.0.1.dist-info/LICENSE
PrintWithColor-0.0.1.dist-info/METADATA
PrintWithColor-0.0.1.dist-info/WHEEL
PrintWithColor-0.0.1.dist-info/top_level.txt
PrintWithColor-0.0.1.dist-info/RECORD
